<?xml version="1.0" encoding="UTF-8" standalone="no"?>
<entry number="597">
  
  <lemma>feric</lemma>
   
  <!-- Assuming feree -> feric -->
  
  <verb_class>I</verb_class>
  
  <pos>vb.</pos>
  
  <variants>[mgl. feric auch „verleumden“, ir. ferec?]</variants>
   
  <!-- Assuming ferek? -> ferec? -->
  
  <definition>„beschlagen“</definition>
  
  <etymology>
    
    <etymon lang="Lat">*FERRICO, -ARE</etymon>
     
    <!-- Assuming *r£rrico -> *FERRICO -->
    
    <cognates>
      
      <form lang="a-frz">enfergier?</form>
      .

    </cognates>
    
  </etymology>
  
  <variants>[ar. încalț].</variants>
   
  <!-- Assuming nealtsu -> încalț -->
  
</entry>
